pytexexam/__init__.py
pytexexam/jinja2env.py
pytexexam/builder/__init__.py
pytexexam/builder/generator.py
pytexexam/component/__init__.py
pytexexam/component/component.py
pytexexam/component/component_group.py
pytexexam/component/mcq_question.py
pytexexam/component/mpart_question.py
pytexexam/component/open_question.py
pytexexam/component/text.py
pytexexam/latex_util/__init__.py
pytexexam/latex_util/component.py
pytexexam/latex_util/internal.py
pytexexam/latex_util/preamble.py
pytexexam/templates/answer/mcq.tex
pytexexam/templates/answer/mpart.tex
pytexexam/templates/answer/open_question.tex
pytexexam/templates/exam/mcq.tex
pytexexam/templates/exam/mpart.tex
pytexexam/templates/exam/open_question.tex
pytexexam/templates/generator/answer.tex
pytexexam/templates/generator/exam.tex
pytexexam/templates/latex_util/add_multiple_package.tex
pytexexam/templates/latex_util/add_package_with_options.tex
pytexexam/templates/latex_util/ams_math_package.tex
pytexexam/templates/latex_util/bold_title.tex
pytexexam/templates/latex_util/geometry_package.tex
pytexexam/templates/latex_util/two_column_header.tex
pytexexam/templates/solution/mcq.tex
pytexexam/templates/solution/mpart.tex
pytexexam/templates/solution/open_question.tex
pytexexam-3.0.1.dist-info/LICENSE.txt
pytexexam-3.0.1.dist-info/METADATA
pytexexam-3.0.1.dist-info/WHEEL
pytexexam-3.0.1.dist-info/top_level.txt
pytexexam-3.0.1.dist-info/RECORD
