Metadata-Version: 2.1
Name: pytexexam
Version: 3.0.1
Summary: A simple library to create latex exam in python 
Home-page: https://github.com/vungocbinh2009/pytexexam
Author: binh
Author-email: vungocbinh@protonmail.com
License: Apache License, Version 2.0
License-File: LICENSE.txt
Requires-Dist: jinja2
Requires-Dist: typing-extensions
